clickui/__init__.py
clickui/const.py
clickui/core.py
clickui/decorators.py
clickui_unofficial-0.5.1.dist-info/LICENSE.rst
clickui_unofficial-0.5.1.dist-info/METADATA
clickui_unofficial-0.5.1.dist-info/WHEEL
clickui_unofficial-0.5.1.dist-info/top_level.txt
clickui_unofficial-0.5.1.dist-info/RECORD
