Metadata-Version: 2.1
Name: clickui-unofficial
Version: 0.5.1
Summary: Unofficial UI wrapper on click commands
Home-page: UNKNOWN
Author: Rakesh Bute
Author-email: 
License: BSD-3-Clause
Project-URL: Code, https://github.com/rbute/clickui-unofficial
Platform: UNKNOWN
Classifier: Programming Language :: Python :: 3
Classifier: Programming Language :: Python
Classifier: Intended Audience :: Developers
Classifier: License :: OSI Approved :: BSD License
Classifier: Operating System :: OS Independent
Requires-Python: >=3.*
Requires-Dist: click
Requires-Dist: tkcalendar
